stock_dataframe/__init__.py
stock_dataframe/dataframe.py
stock_dataframe-0.1.0.dist-info/METADATA
stock_dataframe-0.1.0.dist-info/WHEEL
stock_dataframe-0.1.0.dist-info/top_level.txt
stock_dataframe-0.1.0.dist-info/RECORD
