Metadata-Version: 2.1
Name: stock-dataframe
Version: 0.1.0
Summary: DataFrame with inline stock indicators support.
Home-page: https://github.com/kaelzhang/stock-dataframe
Author: Kael Zhang
Author-email: i+pypi@kael.me
License: MIT
Keywords: pandas pandas-dataframe stock stat indicators macd
Platform: UNKNOWN
Classifier: Programming Language :: Python
Classifier: Programming Language :: Python :: 2.7
Classifier: Programming Language :: Python :: 3.5
Classifier: Programming Language :: Python :: 3.6
Classifier: Programming Language :: Python :: 3.7
Classifier: Programming Language :: Python :: 3.8
Classifier: Programming Language :: Python :: Implementation :: CPython
Classifier: Natural Language :: English
Classifier: Intended Audience :: Developers
Classifier: Intended Audience :: Financial and Insurance Industry
Classifier: Operating System :: OS Independent
Classifier: Development Status :: 4 - Beta
Classifier: Topic :: Utilities
Classifier: License :: OSI Approved :: Apache Software License
Requires-Python: >=2.7
Requires-Dist: numpy (>=1.9.2)
Requires-Dist: pandas (>=0.18.1)
Requires-Dist: int-date (>=0.1.7)
